{"is_source_file": true, "format": "JavaScript", "description": "This file is a bundled JavaScript source for Bootstrap v5.3.8, containing module definitions, components (like alert, button, collapse, carousel), utilities, and core behaviors. It includes code for DOM manipulation, event handling, component logic, and plugin initialization, serving as a comprehensive bootstrap JavaScript library.", "external_files": ["https://getbootstrap.com/", "https://github.com/twbs/bootstrap/blob/main/LICENSE", "https://github.com/twbs/bootstrap/graphs/contributors"], "external_methods": ["CSS.escape", "getComputedStyle", "JSON.parse"], "published": ["Data", "EventHandler", "Manipulator", "defineJQueryPlugin", "Alert", "Button", "Carousel", "Collapse", "Swipe", "SelectorEngine", "getjQuery", "execute", "executeAfterTransition", "hydrateObj", "Tab", "Toast"], "classes": [{"name": "Config", "description": "Base class for configuration management in Bootstrap components, handling default configs, type checking, and merging user options."}, {"name": "BaseComponent", "description": "Superclass for Bootstrap components implementing lifecycle management, configuration, and data handling."}, {"name": "Alert", "description": "Bootstrap alert component class, handling dismissible alerts with show/hide logic."}, {"name": "Button", "description": "Bootstrap button component class, managing toggle states."}, {"name": "Carousel", "description": "Bootstrap carousel implementation for cycling through elements with controls, indicators, and swipe support."}, {"name": "Collapse", "description": "Bootstrap collapse component for show/hide behavior of content sections."}, {"name": "Swipe", "description": "Utility class for detecting swipe gestures on touch-enabled devices."}, {"name": "Tab", "description": "Class handling tab navigation, including show/hide logic, keyboard navigation, and ARIA attributes."}, {"name": "Toast", "description": "Class providing toast notification functionalities including show, hide, and auto-dismiss."}], "methods": [{"name": "set", "description": "Assigns an instance to a DOM element for Bootstrap component management (part of Data API)."}, {"name": "get", "description": "Retrieves stored instance associated with a DOM element."}, {"name": "remove", "description": "Removes stored instance from a DOM element."}, {"name": "AnonymousFunction9427d3740100()", "scope": "", "scopeKind": "", "description": "unavailable"}, {"name": "AnonymousFunction9427d3740200(event)", "scope": "AnonymousFunction9427d3740100.addHandler", "scopeKind": "function", "description": "unavailable"}, {"name": "AnonymousFunction9427d3740300(event)", "scope": "", "scopeKind": "", "description": "unavailable"}, {"name": "AnonymousFunction9427d3740400()", "scope": "AnonymousFunction9427d3740100.Alert.jQueryInterface", "scopeKind": "function", "description": "unavailable"}, {"name": "AnonymousFunction9427d3740500()", "scope": "AnonymousFunction9427d3740100.Button.jQueryInterface", "scopeKind": "function", "description": "unavailable"}, {"name": "AnonymousFunction9427d3740600()", "scope": "AnonymousFunction9427d3740100.Carousel.jQueryInterface", "scopeKind": "function", "description": "unavailable"}, {"name": "AnonymousFunction9427d3740700(event)", "scope": "", "scopeKind": "", "description": "unavailable"}, {"name": "AnonymousFunction9427d3740800()", "scope": "AnonymousFunction9427d3740100.Collapse.jQueryInterface", "scopeKind": "function", "description": "unavailable"}, {"name": "AnonymousFunction9427d3740900(event)", "scope": "", "scopeKind": "", "description": "unavailable"}, {"name": "AnonymousFunction9427d3740a00(acc, placement)", "scope": "AnonymousFunction9427d3740100", "scopeKind": "function", "description": "unavailable"}, {"name": "AnonymousFunction9427d3740b00(acc, placement)", "scope": "AnonymousFunction9427d3740100", "scopeKind": "function", "description": "unavailable"}, {"name": "AnonymousFunction9427d3740c00(name)", "scope": "", "scopeKind": "", "description": "unavailable"}, {"name": "AnonymousFunction9427d3740d00(name)", "scope": "", "scopeKind": "", "description": "unavailable"}, {"name": "AnonymousFunction9427d3740e00()", "scope": "AnonymousFunction9427d3740100.effect$2", "scopeKind": "function", "description": "unavailable"}, {"name": "AnonymousFunction9427d3740f00(name)", "scope": "", "scopeKind": "", "description": "unavailable"}, {"name": "AnonymousFunction9427d3741000(style, property)", "scope": "AnonymousFunction9427d3740f00", "scopeKind": "function", "description": "unavailable"}, {"name": "AnonymousFunction9427d3741100(attribute)", "scope": "", "scopeKind": "", "description": "unavailable"}, {"name": "AnonymousFunction9427d3741200(item)", "scope": "", "scopeKind": "", "description": "unavailable"}, {"name": "AnonymousFunction9427d3741300(hashMap, key)", "scope": "", "scopeKind": "", "description": "unavailable"}, {"name": "AnonymousFunction9427d3741400(scrollParent)", "scope": "", "scopeKind": "", "description": "unavailable"}, {"name": "AnonymousFunction9427d3741500()", "scope": "AnonymousFunction9427d3740100.effect", "scopeKind": "function", "description": "unavailable"}, {"name": "AnonymousFunction9427d3741600(scrollParent)", "scope": "", "scopeKind": "", "description": "unavailable"}, {"name": "AnonymousFunction9427d3741700(matched)", "scope": "", "scopeKind": "", "description": "unavailable"}, {"name": "AnonymousFunction9427d3741800(matched)", "scope": "", "scopeKind": "", "description": "unavailable"}, {"name": "AnonymousFunction9427d3741900(clippingParent)", "scope": "", "scopeKind": "", "description": "unavailable"}, {"name": "AnonymousFunction9427d3741a00(accRect, clippingParent)", "scope": "AnonymousFunction9427d3740100.getClippingRect", "scopeKind": "function", "description": "unavailable"}, {"name": "AnonymousFunction9427d3741b00(key)", "scope": "", "scopeKind": "", "description": "unavailable"}, {"name": "AnonymousFunction9427d3741c00(placement)", "scope": "AnonymousFunction9427d3740100.computeAutoPlacement", "scopeKind": "function", "description": "unavailable"}, {"name": "AnonymousFunction9427d3741d00(placement)", "scope": "AnonymousFunction9427d3740100.computeAutoPlacement", "scopeKind": "function", "description": "unavailable"}, {"name": "AnonymousFunction9427d3741e00(acc, placement)", "scope": "AnonymousFunction9427d3740100.computeAutoPlacement", "scopeKind": "function", "description": "unavailable"}, {"name": "AnonymousFunction9427d3741f00(a, b)", "scope": "", "scopeKind": "", "description": "unavailable"}, {"name": "AnonymousFunction9427d3742000(acc, placement)", "scope": "AnonymousFunction9427d3740100.flip", "scopeKind": "function", "description": "unavailable"}, {"name": "AnonymousFunction9427d3742100(check)", "scope": "AnonymousFunction9427d3740100.flip", "scopeKind": "function", "description": "unavailable"}, {"name": "AnonymousFunction9427d3742200(placement)", "scope": "AnonymousFunction9427d3740100.flip._loop", "scopeKind": "function", "description": "unavailable"}, {"name": "AnonymousFunction9427d3742300(check)", "scope": "", "scopeKind": "", "description": "unavailable"}, {"name": "AnonymousFunction9427d3742400(side)", "scope": "", "scopeKind": "", "description": "unavailable"}, {"name": "AnonymousFunction9427d3742500(acc, placement)", "scope": "AnonymousFunction9427d3740100.offset", "scopeKind": "function", "description": "unavailable"}, {"name": "AnonymousFunction9427d3742600(modifier)", "scope": "", "scopeKind": "", "description": "unavailable"}, {"name": "AnonymousFunction9427d3742700(dep)", "scope": "", "scopeKind": "", "description": "unavailable"}, {"name": "AnonymousFunction9427d3742800(modifier)", "scope": "", "scopeKind": "", "description": "unavailable"}, {"name": "AnonymousFunction9427d3742900(acc, phase)", "scope": "", "scopeKind": "", "description": "unavailable"}, {"name": "AnonymousFunction9427d3742a00(modifier)", "scope": "", "scopeKind": "", "description": "unavailable"}, {"name": "AnonymousFunction9427d3742b00()", "scope": "AnonymousFunction9427d3740100.debounce", "scopeKind": "function", "description": "unavailable"}, {"name": "AnonymousFunction9427d3742c00(resolve)", "scope": "AnonymousFunction9427d3740100.debounce.AnonymousFunction9427d3742b00", "scopeKind": "function", "description": "unavailable"}, {"name": "AnonymousFunction9427d3742d00()", "scope": "", "scopeKind": "", "description": "unavailable"}, {"name": "AnonymousFunction9427d3742e00(merged, current)", "scope": "AnonymousFunction9427d3740100.mergeByName", "scopeKind": "function", "description": "unavailable"}, {"name": "AnonymousFunction9427d3742f00(key)", "scope": "", "scopeKind": "", "description": "unavailable"}, {"name": "AnonymousFunction9427d3743000(element)", "scope": "", "scopeKind": "", "description": "unavailable"}, {"name": "AnonymousFunction9427d3743100(m)", "scope": "", "scopeKind": "", "description": "unavailable"}, {"name": "AnonymousFunction9427d3743200(modifier)", "scope": "", "scopeKind": "", "description": "unavailable"}, {"name": "AnonymousFunction9427d3743300()", "scope": "AnonymousFunction9427d3740100.popperGenerator.createPopper.instance", "scopeKind": "function", "description": "unavailable"}, {"name": "AnonymousFunction9427d3743400(resolve)", "scope": "AnonymousFunction9427d3740100.popperGenerator.createPopper.instance.AnonymousFunction9427d3743300", "scopeKind": "function", "description": "unavailable"}, {"name": "AnonymousFunction9427d3743500(state)", "scope": "", "scopeKind": "", "description": "unavailable"}, {"name": "AnonymousFunction9427d3743600(_ref)", "scope": "", "scopeKind": "", "description": "unavailable"}, {"name": "AnonymousFunction9427d3743700(fn)", "scope": "", "scopeKind": "", "description": "unavailable"}, {"name": "AnonymousFunction9427d3743800()", "scope": "AnonymousFunction9427d3740100.Dropdown.jQueryInterface", "scopeKind": "function", "description": "unavailable"}, {"name": "AnonymousFunction9427d3743900(event)", "scope": "", "scopeKind": "", "description": "unavailable"}, {"name": "AnonymousFunction9427d3743a00()", "scope": "AnonymousFunction9427d3740100.Modal.jQueryInterface", "scopeKind": "function", "description": "unavailable"}, {"name": "AnonymousFunction9427d3743b00(event)", "scope": "", "scopeKind": "", "description": "unavailable"}, {"name": "AnonymousFunction9427d3743c00()", "scope": "AnonymousFunction9427d3740100.Offcanvas.jQueryInterface", "scopeKind": "function", "description": "unavailable"}, {"name": "AnonymousFunction9427d3743d00(event)", "scope": "", "scopeKind": "", "description": "unavailable"}, {"name": "AnonymousFunction9427d3743e00()", "scope": "AnonymousFunction9427d3740100.Tooltip.jQueryInterface", "scopeKind": "function", "description": "unavailable"}, {"name": "AnonymousFunction9427d3743f00()", "scope": "AnonymousFunction9427d3740100.Popover.jQueryInterface", "scopeKind": "function", "description": "unavailable"}, {"name": "AnonymousFunction9427d3744000()", "scope": "AnonymousFunction9427d3740100.ScrollSpy.jQueryInterface", "scopeKind": "function", "description": "unavailable"}, {"name": "AnonymousFunction9427d3744100()", "scope": "AnonymousFunction9427d3740100.Tab.jQueryInterface", "scopeKind": "function", "description": "unavailable"}, {"name": "AnonymousFunction9427d3744200(event)", "scope": "", "scopeKind": "", "description": "unavailable"}, {"name": "AnonymousFunction9427d3744300()", "scope": "AnonymousFunction9427d3740100.Toast.jQueryInterface", "scopeKind": "function", "description": "unavailable"}], "calls": ["EventHandler.on", "EventHandler.off", "EventHandler.trigger", "SelectorEngine.find", "SelectorEngine.findOne", "SelectorEngine.getElementFromSelector", "reflow", "getTransitionDurationFromElement", "CSS.escape", "getjQuery", "execute", "executeAfterTransition", "hydrateObj"], "search-terms": ["bootstrap component", "alert dismiss", "carousel cycle", "collapse toggle", "js bootstrap bundle", "touch swipe", "bootstrap data management", "bootstrap utility functions", "bootstrap event handler", "tab navigation", "toast notification"], "state": 2, "file_id": 540, "knowledge_revision": 1319, "git_revision": "25aa8cc0b32f0d1a54be575347e6d84b70b1acd7", "ctags": [{"_type": "tag", "name": "*", "path": "/home/kavia/workspace/code-generation/bootstrap-2367/dist/js/bootstrap.bundle.js", "pattern": "/^    '*': ['class', 'dir', 'id', 'lang', 'role', ARIA_ATTRIBUTE_PATTERN],$/", "language": "JavaScript", "kind": "property", "scope": "AnonymousFunction9427d3740100.DefaultAllowlist", "scopeKind": "class"}, {"_type": "tag", "name": "AUTO", "path": "/home/kavia/workspace/code-generation/bootstrap-2367/dist/js/bootstrap.bundle.js", "pattern": "/^    AUTO: 'auto',$/", "language": "JavaScript", "kind": "property", "scope": "AnonymousFunction9427d3740100.AttachmentMap", "scopeKind": "class"}, {"_type": "tag", "name": "Alert", "path": "/home/kavia/workspace/code-generation/bootstrap-2367/dist/js/bootstrap.bundle.js", "pattern": "/^    Alert,$/", "language": "JavaScript", "kind": "field", "scope": "AnonymousFunction9427d3740100.index_umd", "scopeKind": "class"}, {"_type": "tag", "name": "Alert", "path": "/home/kavia/workspace/code-generation/bootstrap-2367/dist/js/bootstrap.bundle.js", "pattern": "/^  class Alert extends BaseComponent {$/", "language": "JavaScript", "kind": "class", "scope": "AnonymousFunction9427d3740100", "scopeKind": "class"}, {"_type": "tag", "name": "AnonymousFunction9427d3740100", "path": "/home/kavia/workspace/code-generation/bootstrap-2367/dist/js/bootstrap.bundle.js", "pattern": "/^})(this, (function () { 'use strict';$/", "language": "JavaScript", "kind": "function", "signature": "()"}, {"_type": "tag", "name": "AnonymousFunction9427d3740200", "path": "/home/kavia/workspace/code-generation/bootstrap-2367/dist/js/bootstrap.bundle.js", "pattern": "/^        return function (event) {$/", "language": "JavaScript", "kind": "function", "signature": "(event)", "scope": "AnonymousFunction9427d3740100.addHandler", "scopeKind": "function"}, {"_type": "tag", "name": "AnonymousFunction9427d3740300", "path": "/home/kavia/workspace/code-generation/bootstrap-2367/dist/js/bootstrap.bundle.js", "pattern": "/^    EventHandler.on(document, clickEvent, `[data-bs-dismiss=\"${name}\"]`, function (event) {$/", "language": "JavaScript", "kind": "function", "signature": "(event)"}, {"_type": "tag", "name": "AnonymousFunction9427d3740400", "path": "/home/kavia/workspace/code-generation/bootstrap-2367/dist/js/bootstrap.bundle.js", "pattern": "/^      return this.each(function () {$/", "language": "JavaScript", "kind": "function", "signature": "()", "scope": "AnonymousFunction9427d3740100.Alert.jQueryInterface", "scopeKind": "function"}, {"_type": "tag", "name": "AnonymousFunction9427d3740500", "path": "/home/kavia/workspace/code-generation/bootstrap-2367/dist/js/bootstrap.bundle.js", "pattern": "/^      return this.each(function () {$/", "language": "JavaScript", "kind": "function", "signature": "()", "scope": "AnonymousFunction9427d3740100.Button.jQueryInterface", "scopeKind": "function"}, {"_type": "tag", "name": "AnonymousFunction9427d3740600", "path": "/home/kavia/workspace/code-generation/bootstrap-2367/dist/js/bootstrap.bundle.js", "pattern": "/^      return this.each(function () {$/", "language": "JavaScript", "kind": "function", "signature": "()", "scope": "AnonymousFunction9427d3740100.Carousel.jQueryInterface", "scopeKind": "function"}, {"_type": "tag", "name": "AnonymousFunction9427d3740700", "path": "/home/kavia/workspace/code-generation/bootstrap-2367/dist/js/bootstrap.bundle.js", "pattern": "/^  EventHandler.on(document, EVENT_CLICK_DATA_API$5, SELECTOR_DATA_SLIDE, function (event) {$/", "language": "JavaScript", "kind": "function", "signature": "(event)"}, {"_type": "tag", "name": "AnonymousFunction9427d3740800", "path": "/home/kavia/workspace/code-generation/bootstrap-2367/dist/js/bootstrap.bundle.js", "pattern": "/^      return this.each(function () {$/", "language": "JavaScript", "kind": "function", "signature": "()", "scope": "AnonymousFunction9427d3740100.Collapse.jQueryInterface", "scopeKind": "function"}, {"_type": "tag", "name": "AnonymousFunction9427d3740900", "path": "/home/kavia/workspace/code-generation/bootstrap-2367/dist/js/bootstrap.bundle.js", "pattern": "/^  EventHandler.on(document, EVENT_CLICK_DATA_API$4, SELECTOR_DATA_TOGGLE$4, function (event) {$/", "language": "JavaScript", "kind": "function", "signature": "(event)"}, {"_type": "tag", "name": "AnonymousFunction9427d3740a00", "path": "/home/kavia/workspace/code-generation/bootstrap-2367/dist/js/bootstrap.bundle.js", "pattern": "/^  var variationPlacements = \\/*#__PURE__*\\/basePlacements.reduce(function (acc, placement) {$/", "language": "JavaScript", "kind": "function", "signature": "(acc, placement)", "scope": "AnonymousFunction9427d3740100", "scopeKind": "function"}, {"_type": "tag", "name": "AnonymousFunction9427d3740b00", "path": "/home/kavia/workspace/code-generation/bootstrap-2367/dist/js/bootstrap.bundle.js", "pattern": "/^  var placements = \\/*#__PURE__*\\/[].concat(basePlacements, [auto]).reduce(function (acc, placem/", "language": "JavaScript", "kind": "function", "signature": "(acc, placement)", "scope": "AnonymousFunction9427d3740100", "scopeKind": "function"}, {"_type": "tag", "name": "AnonymousFunction9427d3740c00", "path": "/home/kavia/workspace/code-generation/bootstrap-2367/dist/js/bootstrap.bundle.js", "pattern": "/^    Object.keys(state.elements).forEach(function (name) {$/", "language": "JavaScript", "kind": "function", "signature": "(name)"}, {"_type": "tag", "name": "AnonymousFunction9427d3740d00", "path": "/home/kavia/workspace/code-generation/bootstrap-2367/dist/js/bootstrap.bundle.js", "pattern": "/^      Object.keys(attributes).forEach(function (name) {$/", "language": "JavaScript", "kind": "function", "signature": "(name)"}, {"_type": "tag", "name": "AnonymousFunction9427d3740e00", "path": "/home/kavia/workspace/code-generation/bootstrap-2367/dist/js/bootstrap.bundle.js", "pattern": "/^    return function () {$/", "language": "JavaScript", "kind": "function", "signature": "()", "scope": "AnonymousFunction9427d3740100.effect$2", "scopeKind": "function"}, {"_type": "tag", "name": "AnonymousFunction9427d3740f00", "path": "/home/kavia/workspace/code-generation/bootstrap-2367/dist/js/bootstrap.bundle.js", "pattern": "/^      Object.keys(state.elements).forEach(function (name) {$/", "language": "JavaScript", "kind": "function", "signature": "(name)"}, {"_type": "tag", "name": "AnonymousFunction9427d3741000", "path": "/home/kavia/workspace/code-generation/bootstrap-2367/dist/js/bootstrap.bundle.js", "pattern": "/^        var style = styleProperties.reduce(function (style, property) {$/", "language": "JavaScript", "kind": "function", "signature": "(style, property)", "scope": "AnonymousFunction9427d3740f00", "scopeKind": "function"}, {"_type": "tag", "name": "AnonymousFunction9427d3741100", "path": "/home/kavia/workspace/code-generation/bootstrap-2367/dist/js/bootstrap.bundle.js", "pattern": "/^        Object.keys(attributes).forEach(function (attribute) {$/", "language": "JavaScript", "kind": "function", "signature": "(attribute)"}, {"_type": "tag", "name": "AnonymousFunction9427d3741200", "path": "/home/kavia/workspace/code-generation/bootstrap-2367/dist/js/bootstrap.bundle.js", "pattern": "/^      return uaData.brands.map(function (item) {$/", "language": "JavaScript", "kind": "function", "signature": "(item)"}, {"_type": "tag", "name": "AnonymousFunction9427d3741300", "path": "/home/kavia/workspace/code-generation/bootstrap-2367/dist/js/bootstrap.bundle.js", "pattern": "/^    return keys.reduce(function (hashMap, key) {$/", "language": "JavaScript", "kind": "function", "signature": "(hashMap, key)"}, {"_type": "tag", "name": "AnonymousFunction9427d3741400", "path": "/home/kavia/workspace/code-generation/bootstrap-2367/dist/js/bootstrap.bundle.js", "pattern": "/^      scrollParents.forEach(function (scrollParent) {$/", "language": "JavaScript", "kind": "function", "signature": "(scrollParent)"}, {"_type": "tag", "name": "AnonymousFunction9427d3741500", "path": "/home/kavia/workspace/code-generation/bootstrap-2367/dist/js/bootstrap.bundle.js", "pattern": "/^    return function () {$/", "language": "JavaScript", "kind": "function", "signature": "()", "scope": "AnonymousFunction9427d3740100.effect", "scopeKind": "function"}, {"_type": "tag", "name": "AnonymousFunction9427d3741600", "path": "/home/kavia/workspace/code-generation/bootstrap-2367/dist/js/bootstrap.bundle.js", "pattern": "/^        scrollParents.forEach(function (scrollParent) {$/", "language": "JavaScript", "kind": "function", "signature": "(scrollParent)"}, {"_type": "tag", "name": "AnonymousFunction9427d3741700", "path": "/home/kavia/workspace/code-generation/bootstrap-2367/dist/js/bootstrap.bundle.js", "pattern": "/^    return placement.replace(\\/left|right|bottom|top\\/g, function (matched) {$/", "language": "JavaScript", "kind": "function", "signature": "(matched)"}, {"_type": "tag", "name": "AnonymousFunction9427d3741800", "path": "/home/kavia/workspace/code-generation/bootstrap-2367/dist/js/bootstrap.bundle.js", "pattern": "/^    return placement.replace(\\/start|end\\/g, function (matched) {$/", "language": "JavaScript", "kind": "function", "signature": "(matched)"}, {"_type": "tag", "name": "AnonymousFunction9427d3741900", "path": "/home/kavia/workspace/code-generation/bootstrap-2367/dist/js/bootstrap.bundle.js", "pattern": "/^    return clippingParents.filter(function (clippingParent) {$/", "language": "JavaScript", "kind": "function", "signature": "(clippingParent)"}, {"_type": "tag", "name": "AnonymousFunction9427d3741a00", "path": "/home/kavia/workspace/code-generation/bootstrap-2367/dist/js/bootstrap.bundle.js", "pattern": "/^    var clippingRect = clippingParents.reduce(function (accRect, clippingParent) {$/", "language": "JavaScript", "kind": "function", "signature": "(accRect, clippingParent)", "scope": "AnonymousFunction9427d3740100.getClippingRect", "scopeKind": "function"}, {"_type": "tag", "name": "AnonymousFunction9427d3741b00", "path": "/home/kavia/workspace/code-generation/bootstrap-2367/dist/js/bootstrap.bundle.js", "pattern": "/^      Object.keys(overflowOffsets).forEach(function (key) {$/", "language": "JavaScript", "kind": "function", "signature": "(key)"}, {"_type": "tag", "name": "AnonymousFunction9427d3741c00", "path": "/home/kavia/workspace/code-generation/bootstrap-2367/dist/js/bootstrap.bundle.js", "pattern": "/^    var placements$1 = variation ? flipVariations ? variationPlacements : variationPlacements.fi/", "language": "JavaScript", "kind": "function", "signature": "(placement)", "scope": "AnonymousFunction9427d3740100.computeAutoPlacement", "scopeKind": "function"}, {"_type": "tag", "name": "AnonymousFunction9427d3741d00", "path": "/home/kavia/workspace/code-generation/bootstrap-2367/dist/js/bootstrap.bundle.js", "pattern": "/^    var allowedPlacements = placements$1.filter(function (placement) {$/", "language": "JavaScript", "kind": "function", "signature": "(placement)", "scope": "AnonymousFunction9427d3740100.computeAutoPlacement", "scopeKind": "function"}, {"_type": "tag", "name": "AnonymousFunction9427d3741e00", "path": "/home/kavia/workspace/code-generation/bootstrap-2367/dist/js/bootstrap.bundle.js", "pattern": "/^    var overflows = allowedPlacements.reduce(function (acc, placement) {$/", "language": "JavaScript", "kind": "function", "signature": "(acc, placement)", "scope": "AnonymousFunction9427d3740100.computeAutoPlacement", "scopeKind": "function"}, {"_type": "tag", "name": "AnonymousFunction9427d3741f00", "path": "/home/kavia/workspace/code-generation/bootstrap-2367/dist/js/bootstrap.bundle.js", "pattern": "/^    return Object.keys(overflows).sort(function (a, b) {$/", "language": "JavaScript", "kind": "function", "signature": "(a, b)"}, {"_type": "tag", "name": "AnonymousFunction9427d3742000", "path": "/home/kavia/workspace/code-generation/bootstrap-2367/dist/js/bootstrap.bundle.js", "pattern": "/^    var placements = [preferredPlacement].concat(fallbackPlacements).reduce(function (acc, place/", "language": "JavaScript", "kind": "function", "signature": "(acc, placement)", "scope": "AnonymousFunction9427d3740100.flip", "scopeKind": "function"}, {"_type": "tag", "name": "AnonymousFunction9427d3742100", "path": "/home/kavia/workspace/code-generation/bootstrap-2367/dist/js/bootstrap.bundle.js", "pattern": "/^      if (checks.every(function (check) {$/", "language": "JavaScript", "kind": "function", "signature": "(check)", "scope": "AnonymousFunction9427d3740100.flip", "scopeKind": "function"}, {"_type": "tag", "name": "AnonymousFunction9427d3742200", "path": "/home/kavia/workspace/code-generation/bootstrap-2367/dist/js/bootstrap.bundle.js", "pattern": "/^        var fittingPlacement = placements.find(function (placement) {$/", "language": "JavaScript", "kind": "function", "signature": "(placement)", "scope": "AnonymousFunction9427d3740100.flip._loop", "scopeKind": "function"}, {"_type": "tag", "name": "AnonymousFunction9427d3742300", "path": "/home/kavia/workspace/code-generation/bootstrap-2367/dist/js/bootstrap.bundle.js", "pattern": "/^            return checks.slice(0, _i).every(function (check) {$/", "language": "JavaScript", "kind": "function", "signature": "(check)"}, {"_type": "tag", "name": "AnonymousFunction9427d3742400", "path": "/home/kavia/workspace/code-generation/bootstrap-2367/dist/js/bootstrap.bundle.js", "pattern": "/^    return [top, right, bottom, left].some(function (side) {$/", "language": "JavaScript", "kind": "function", "signature": "(side)"}, {"_type": "tag", "name": "AnonymousFunction9427d3742500", "path": "/home/kavia/workspace/code-generation/bootstrap-2367/dist/js/bootstrap.bundle.js", "pattern": "/^    var data = placements.reduce(function (acc, placement) {$/", "language": "JavaScript", "kind": "function", "signature": "(acc, placement)", "scope": "AnonymousFunction9427d3740100.offset", "scopeKind": "function"}, {"_type": "tag", "name": "AnonymousFunction9427d3742600", "path": "/home/kavia/workspace/code-generation/bootstrap-2367/dist/js/bootstrap.bundle.js", "pattern": "/^    modifiers.forEach(function (modifier) {$/", "language": "JavaScript", "kind": "function", "signature": "(modifier)"}, {"_type": "tag", "name": "AnonymousFunction9427d3742700", "path": "/home/kavia/workspace/code-generation/bootstrap-2367/dist/js/bootstrap.bundle.js", "pattern": "/^      requires.forEach(function (dep) {$/", "language": "JavaScript", "kind": "function", "signature": "(dep)"}, {"_type": "tag", "name": "AnonymousFunction9427d3742800", "path": "/home/kavia/workspace/code-generation/bootstrap-2367/dist/js/bootstrap.bundle.js", "pattern": "/^    modifiers.forEach(function (modifier) {$/", "language": "JavaScript", "kind": "function", "signature": "(modifier)"}, {"_type": "tag", "name": "AnonymousFunction9427d3742900", "path": "/home/kavia/workspace/code-generation/bootstrap-2367/dist/js/bootstrap.bundle.js", "pattern": "/^    return modifierPhases.reduce(function (acc, phase) {$/", "language": "JavaScript", "kind": "function", "signature": "(acc, phase)"}, {"_type": "tag", "name": "AnonymousFunction9427d3742a00", "path": "/home/kavia/workspace/code-generation/bootstrap-2367/dist/js/bootstrap.bundle.js", "pattern": "/^      return acc.concat(orderedModifiers.filter(function (modifier) {$/", "language": "JavaScript", "kind": "function", "signature": "(modifier)"}, {"_type": "tag", "name": "AnonymousFunction9427d3742b00", "path": "/home/kavia/workspace/code-generation/bootstrap-2367/dist/js/bootstrap.bundle.js", "pattern": "/^    return function () {$/", "language": "JavaScript", "kind": "function", "signature": "()", "scope": "AnonymousFunction9427d3740100.debounce", "scopeKind": "function"}, {"_type": "tag", "name": "AnonymousFunction9427d3742c00", "path": "/home/kavia/workspace/code-generation/bootstrap-2367/dist/js/bootstrap.bundle.js", "pattern": "/^        pending = new Promise(function (resolve) {$/", "language": "JavaScript", "kind": "function", "signature": "(resolve)", "scope": "AnonymousFunction9427d3740100.debounce.AnonymousFunction9427d3742b00", "scopeKind": "function"}, {"_type": "tag", "name": "AnonymousFunction9427d3742d00", "path": "/home/kavia/workspace/code-generation/bootstrap-2367/dist/js/bootstrap.bundle.js", "pattern": "/^          Promise.resolve().then(function () {$/", "language": "JavaScript", "kind": "function", "signature": "()"}, {"_type": "tag", "name": "AnonymousFunction9427d3742e00", "path": "/home/kavia/workspace/code-generation/bootstrap-2367/dist/js/bootstrap.bundle.js", "pattern": "/^    var merged = modifiers.reduce(function (merged, current) {$/", "language": "JavaScript", "kind": "function", "signature": "(merged, current)", "scope": "AnonymousFunction9427d3740100.mergeByName", "scopeKind": "function"}, {"_type": "tag", "name": "AnonymousFunction9427d3742f00", "path": "/home/kavia/workspace/code-generation/bootstrap-2367/dist/js/bootstrap.bundle.js", "pattern": "/^    return Object.keys(merged).map(function (key) {$/", "language": "JavaScript", "kind": "function", "signature": "(key)"}, {"_type": "tag", "name": "AnonymousFunction9427d3743000", "path": "/home/kavia/workspace/code-generation/bootstrap-2367/dist/js/bootstrap.bundle.js", "pattern": "/^    return !args.some(function (element) {$/", "language": "JavaScript", "kind": "function", "signature": "(element)"}, {"_type": "tag", "name": "AnonymousFunction9427d3743100", "path": "/home/kavia/workspace/code-generation/bootstrap-2367/dist/js/bootstrap.bundle.js", "pattern": "/^          state.orderedModifiers = orderedModifiers.filter(function (m) {$/", "language": "JavaScript", "kind": "function", "signature": "(m)"}, {"_type": "tag", "name": "AnonymousFunction9427d3743200", "path": "/home/kavia/workspace/code-generation/bootstrap-2367/dist/js/bootstrap.bundle.js", "pattern": "/^          state.orderedModifiers.forEach(function (modifier) {$/", "language": "JavaScript", "kind": "function", "signature": "(modifier)"}, {"_type": "tag", "name": "AnonymousFunction9427d3743300", "path": "/home/kavia/workspace/code-generation/bootstrap-2367/dist/js/bootstrap.bundle.js", "pattern": "/^        update: debounce(function () {$/", "language": "JavaScript", "kind": "function", "signature": "()", "scope": "AnonymousFunction9427d3740100.popperGenerator.createPopper.instance", "scopeKind": "function"}, {"_type": "tag", "name": "AnonymousFunction9427d3743400", "path": "/home/kavia/workspace/code-generation/bootstrap-2367/dist/js/bootstrap.bundle.js", "pattern": "/^          return new Promise(function (resolve) {$/", "language": "JavaScript", "kind": "function", "signature": "(resolve)", "scope": "AnonymousFunction9427d3740100.popperGenerator.createPopper.instance.AnonymousFunction9427d3743300", "scopeKind": "function"}, {"_type": "tag", "name": "AnonymousFunction9427d3743500", "path": "/home/kavia/workspace/code-generation/bootstrap-2367/dist/js/bootstrap.bundle.js", "pattern": "/^      instance.setOptions(options).then(function (state) {$/", "language": "JavaScript", "kind": "function", "signature": "(state)"}, {"_type": "tag", "name": "AnonymousFunction9427d3743600", "path": "/home/kavia/workspace/code-generation/bootstrap-2367/dist/js/bootstrap.bundle.js", "pattern": "/^        state.orderedModifiers.forEach(function (_ref) {$/", "language": "JavaScript", "kind": "function", "signature": "(_ref)"}, {"_type": "tag", "name": "AnonymousFunction9427d3743700", "path": "/home/kavia/workspace/code-generation/bootstrap-2367/dist/js/bootstrap.bundle.js", "pattern": "/^        effectCleanupFns.forEach(function (fn) {$/", "language": "JavaScript", "kind": "function", "signature": "(fn)"}, {"_type": "tag", "name": "AnonymousFunction9427d3743800", "path": "/home/kavia/workspace/code-generation/bootstrap-2367/dist/js/bootstrap.bundle.js", "pattern": "/^      return this.each(function () {$/", "language": "JavaScript", "kind": "function", "signature": "()", "scope": "AnonymousFunction9427d3740100.Dropdown.jQueryInterface", "scopeKind": "function"}, {"_type": "tag", "name": "AnonymousFunction9427d3743900", "path": "/home/kavia/workspace/code-generation/bootstrap-2367/dist/js/bootstrap.bundle.js", "pattern": "/^  EventHandler.on(document, EVENT_CLICK_DATA_API$3, SELECTOR_DATA_TOGGLE$3, function (event) {$/", "language": "JavaScript", "kind": "function", "signature": "(event)"}, {"_type": "tag", "name": "AnonymousFunction9427d3743a00", "path": "/home/kavia/workspace/code-generation/bootstrap-2367/dist/js/bootstrap.bundle.js", "pattern": "/^      return this.each(function () {$/", "language": "JavaScript", "kind": "function", "signature": "()", "scope": "AnonymousFunction9427d3740100.Modal.jQueryInterface", "scopeKind": "function"}, {"_type": "tag", "name": "AnonymousFunction9427d3743b00", "path": "/home/kavia/workspace/code-generation/bootstrap-2367/dist/js/bootstrap.bundle.js", "pattern": "/^  EventHandler.on(document, EVENT_CLICK_DATA_API$2, SELECTOR_DATA_TOGGLE$2, function (event) {$/", "language": "JavaScript", "kind": "function", "signature": "(event)"}, {"_type": "tag", "name": "AnonymousFunction9427d3743c00", "path": "/home/kavia/workspace/code-generation/bootstrap-2367/dist/js/bootstrap.bundle.js", "pattern": "/^      return this.each(function () {$/", "language": "JavaScript", "kind": "function", "signature": "()", "scope": "AnonymousFunction9427d3740100.Offcanvas.jQueryInterface", "scopeKind": "function"}, {"_type": "tag", "name": "AnonymousFunction9427d3743d00", "path": "/home/kavia/workspace/code-generation/bootstrap-2367/dist/js/bootstrap.bundle.js", "pattern": "/^  EventHandler.on(document, EVENT_CLICK_DATA_API$1, SELECTOR_DATA_TOGGLE$1, function (event) {$/", "language": "JavaScript", "kind": "function", "signature": "(event)"}, {"_type": "tag", "name": "AnonymousFunction9427d3743e00", "path": "/home/kavia/workspace/code-generation/bootstrap-2367/dist/js/bootstrap.bundle.js", "pattern": "/^      return this.each(function () {$/", "language": "JavaScript", "kind": "function", "signature": "()", "scope": "AnonymousFunction9427d3740100.Tooltip.jQueryInterface", "scopeKind": "function"}, {"_type": "tag", "name": "AnonymousFunction9427d3743f00", "path": "/home/kavia/workspace/code-generation/bootstrap-2367/dist/js/bootstrap.bundle.js", "pattern": "/^      return this.each(function () {$/", "language": "JavaScript", "kind": "function", "signature": "()", "scope": "AnonymousFunction9427d3740100.Popover.jQueryInterface", "scopeKind": "function"}, {"_type": "tag", "name": "AnonymousFunction9427d3744000", "path": "/home/kavia/workspace/code-generation/bootstrap-2367/dist/js/bootstrap.bundle.js", "pattern": "/^      return this.each(function () {$/", "language": "JavaScript", "kind": "function", "signature": "()", "scope": "AnonymousFunction9427d3740100.ScrollSpy.jQueryInterface", "scopeKind": "function"}, {"_type": "tag", "name": "AnonymousFunction9427d3744100", "path": "/home/kavia/workspace/code-generation/bootstrap-2367/dist/js/bootstrap.bundle.js", "pattern": "/^      return this.each(function () {$/", "language": "JavaScript", "kind": "function", "signature": "()", "scope": "AnonymousFunction9427d3740100.Tab.jQueryInterface", "scopeKind": "function"}, {"_type": "tag", "name": "AnonymousFunction9427d3744200", "path": "/home/kavia/workspace/code-generation/bootstrap-2367/dist/js/bootstrap.bundle.js", "pattern": "/^  EventHandler.on(document, EVENT_CLICK_DATA_API, SELECTOR_DATA_TOGGLE, function (event) {$/", "language": "JavaScript", "kind": "function", "signature": "(event)"}, {"_type": "tag", "name": "AnonymousFunction9427d3744300", "path": "/home/kavia/workspace/code-generation/bootstrap-2367/dist/js/bootstrap.bundle.js", "pattern": "/^      return this.each(function () {$/", "language": "JavaScript", "kind": "function", "signature": "()", "scope": "AnonymousFunction9427d3740100.Toast.jQueryInterface", "scopeKind": "function"}, {"_type": "tag", "name": "AttachmentMap", "path": "/home/kavia/workspace/code-generation/bootstrap-2367/dist/js/bootstrap.bundle.js", "pattern": "/^  const AttachmentMap = {$/", "language": "JavaScript", "kind": "class", "scope": "AnonymousFunction9427d3740100", "scopeKind": "class"}, {"_type": "tag", "name": "BOTTOM", "path": "/home/kavia/workspace/code-generation/bootstrap-2367/dist/js/bootstrap.bundle.js", "pattern": "/^    BOTTOM: 'bottom',$/", "language": "JavaScript", "kind": "property", "scope": "AnonymousFunction9427d3740100.AttachmentMap", "scopeKind": "class"}, {"_type": "tag", "name": "Backdrop", "path": "/home/kavia/workspace/code-generation/bootstrap-2367/dist/js/bootstrap.bundle.js", "pattern": "/^  class Backdrop extends Config {$/", "language": "JavaScript", "kind": "class", "scope": "AnonymousFunction9427d3740100", "scopeKind": "class"}, {"_type": "tag", "name": "BaseComponent", "path": "/home/kavia/workspace/code-generation/bootstrap-2367/dist/js/bootstrap.bundle.js", "pattern": "/^  class BaseComponent extends Config {$/", "language": "JavaScript", "kind": "class", "scope": "AnonymousFunction9427d3740100", "scopeKind": "class"}, {"_type": "tag", "name": "Button", "path": "/home/kavia/workspace/code-generation/bootstrap-2367/dist/js/bootstrap.bundle.js", "pattern": "/^  class Button extends BaseComponent {$/", "language": "JavaScript", "kind": "class", "scope": "AnonymousFunction9427d3740100", "scopeKind": "class"}, {"_type": "tag", "name": "Carousel", "path": "/home/kavia/workspace/code-generation/bootstrap-2367/dist/js/bootstrap.bundle.js", "pattern": "/^  class Carousel extends BaseComponent {$/", "language": "JavaScript", "kind": "class", "scope": "AnonymousFunction9427d3740100", "scopeKind": "class"}, {"_type": "tag", "name": "Collapse", "path": "/home/kavia/workspace/code-generation/bootstrap-2367/dist/js/bootstrap.bundle.js", "pattern": "/^  class Collapse extends BaseComponent {$/", "language": "JavaScript", "kind": "class", "scope": "AnonymousFunction9427d3740100", "scopeKind": "class"}, {"_type": "tag", "name": "Config", "path": "/home/kavia/workspace/code-generation/bootstrap-2367/dist/js/bootstrap.bundle.js", "pattern": "/^  class Config {$/", "language": "JavaScript", "kind": "class", "scope": "AnonymousFunction9427d3740100", "scopeKind": "class"}, {"_type": "tag", "name": "DATA_KEY", "path": "/home/kavia/workspace/code-generation/bootstrap-2367/dist/js/bootstrap.bundle.js", "pattern": "/^    static get DATA_KEY() {$/", "language": "JavaScript", "kind": "getter", "signature": "()", "scope": "AnonymousFunction9427d3740100.BaseComponent", "scopeKind": "class"}, {"_type": "tag", "name": "DEFAULT_OPTIONS", "path": "/home/kavia/workspace/code-generation/bootstrap-2367/dist/js/bootstrap.bundle.js", "pattern": "/^  var DEFAULT_OPTIONS = {$/", "language": "JavaScript", "kind": "class", "scope": "AnonymousFunction9427d3740100", "scopeKind": "class"}, {"_type": "tag", "name": "Default", "path": "/home/kavia/workspace/code-generation/bootstrap-2367/dist/js/bootstrap.bundle.js", "pattern": "/^    static get Default() {$/", "language": "JavaScript", "kind": "getter", "signature": "()", "scope": "AnonymousFunction9427d3740100.Backdrop", "scopeKind": "class"}, {"_type": "tag", "name": "Default", "path": "/home/kavia/workspace/code-generation/bootstrap-2367/dist/js/bootstrap.bundle.js", "pattern": "/^    static get Default() {$/", "language": "JavaScript", "kind": "getter", "signature": "()", "scope": "AnonymousFunction9427d3740100.Carousel", "scopeKind": "class"}, {"_type": "tag", "name": "Default", "path": "/home/kavia/workspace/code-generation/bootstrap-2367/dist/js/bootstrap.bundle.js", "pattern": "/^    static get Default() {$/", "language": "JavaScript", "kind": "getter", "signature": "()", "scope": "AnonymousFunction9427d3740100.Collapse", "scopeKind": "class"}, {"_type": "tag", "name": "Default", "path": "/home/kavia/workspace/code-generation/bootstrap-2367/dist/js/bootstrap.bundle.js", "pattern": "/^    static get Default() {$/", "language": "JavaScript", "kind": "getter", "signature": "()", "scope": "AnonymousFunction9427d3740100.Config", "scopeKind": "class"}, {"_type": "tag", "name": "Default", "path": "/home/kavia/workspace/code-generation/bootstrap-2367/dist/js/bootstrap.bundle.js", "pattern": "/^    static get Default() {$/", "language": "JavaScript", "kind": "getter", "signature": "()", "scope": "AnonymousFunction9427d3740100.Dropdown", "scopeKind": "class"}, {"_type": "tag", "name": "Default", "path": "/home/kavia/workspace/code-generation/bootstrap-2367/dist/js/bootstrap.bundle.js", "pattern": "/^    static get Default() {$/", "language": "JavaScript", "kind": "getter", "signature": "()", "scope": "AnonymousFunction9427d3740100.FocusTrap", "scopeKind": "class"}, {"_type": "tag", "name": "Default", "path": "/home/kavia/workspace/code-generation/bootstrap-2367/dist/js/bootstrap.bundle.js", "pattern": "/^    static get Default() {$/", "language": "JavaScript", "kind": "getter", "signature": "()", "scope": "AnonymousFunction9427d3740100.Modal", "scopeKind": "class"}, {"_type": "tag", "name": "Default", "path": "/home/kavia/workspace/code-generation/bootstrap-2367/dist/js/bootstrap.bundle.js", "pattern": "/^    static get Default() {$/", "language": "JavaScript", "kind": "getter", "signature": "()", "scope": "AnonymousFunction9427d3740100.Offcanvas", "scopeKind": "class"}, {"_type": "tag", "name": "Default", "path": "/home/kavia/workspace/code-generation/bootstrap-2367/dist/js/bootstrap.bundle.js", "pattern": "/^    static get Default() {$/", "language": "JavaScript", "kind": "getter", "signature": "()", "scope": "AnonymousFunction9427d3740100.Popover", "scopeKind": "class"}, {"_type": "tag", "name": "Default", "path": "/home/kavia/workspace/code-generation/bootstrap-2367/dist/js/bootstrap.bundle.js", "pattern": "/^    static get Default() {$/", "language": "JavaScript", "kind": "getter", "signature": "()", "scope": "AnonymousFunction9427d3740100.ScrollSpy", "scopeKind": "class"}, {"_type": "tag", "name": "Default", "path": "/home/kavia/workspace/code-generation/bootstrap-2367/dist/js/bootstrap.bundle.js", "pattern": "/^    static get Default() {$/", "language": "JavaScript", "kind": "getter", "signature": "()", "scope": "AnonymousFunction9427d3740100.Swipe", "scopeKind": "class"}], "hash": "7d2c412531f05f39e97195f9b48a53dc", "format-version": 4, "code-base-name": "bootstrap-2367", "filename": "dist/js/bootstrap.bundle.js", "fields": [{"name": "'*': ['class', 'dir', 'id', 'lang', 'role', ARIA_ATTRIBUTE_PATTERN],", "scope": "AnonymousFunction9427d3740100.DefaultAllowlist", "scopeKind": "class", "description": "unavailable"}, {"name": "AUTO: 'auto',", "scope": "AnonymousFunction9427d3740100.AttachmentMap", "scopeKind": "class", "description": "unavailable"}, {"name": "Alert,", "scope": "AnonymousFunction9427d3740100.index_umd", "scopeKind": "class", "description": "unavailable"}, {"name": "BOTTOM: 'bottom',", "scope": "AnonymousFunction9427d3740100.AttachmentMap", "scopeKind": "class", "description": "unavailable"}], "revision_history": [{"1319": "25aa8cc0b32f0d1a54be575347e6d84b70b1acd7"}]}