{"is_source_file": true, "format": "JavaScript", "description": "This file is an ES module that imports various Bootstrap component modules and exports them as a default object, serving as an index or entry point for the Bootstrap JavaScript components.", "external_files": ["./src/alert.js", "./src/button.js", "./src/carousel.js", "./src/collapse.js", "./src/dropdown.js", "./src/modal.js", "./src/offcanvas.js", "./src/popover.js", "./src/scrollspy.js", "./src/tab.js", "./src/toast.js", "./src/tooltip.js"], "external_methods": [], "published": ["Alert", "Button", "Carousel", "Collapse", "Dropdown", "Modal", "Offcanvas", "Popover", "ScrollSpy", "Tab", "Toast", "Tooltip"], "classes": [], "methods": [], "calls": ["import Alert from './src/alert.js'", "import Button from './src/button.js'", "import Carousel from './src/carousel.js'", "import Collapse from './src/collapse.js'", "import Dropdown from './src/dropdown.js'", "import Modal from './src/modal.js'", "import Offcanvas from './src/offcanvas.js'", "import Popover from './src/popover.js'", "import ScrollSpy from './src/scrollspy.js'", "import Tab from './src/tab.js'", "import Toast from './src/toast.js'", "import Tooltip from './src/tooltip.js'", "export default { Alert, Button, Carousel, Collapse, Dropdown, Modal, Offcanvas, Popover, ScrollSpy, Tab, Toast, Tooltip }"], "search-terms": ["bootstrap index", "umd", "bootstrap component index", "bootstrap modular import"], "state": 2, "file_id": 302, "knowledge_revision": 609, "git_revision": "842fd50da8fffe5a67d01077abd050757c257776", "ctags": [], "filename": "js/index.umd.js", "hash": "762fac4614c9f11d73a3666d1294724d", "format-version": 4, "code-base-name": "https://github.com/kavia-common/bootstrap-2367.git:kavia-main", "revision_history": [{"609": "842fd50da8fffe5a67d01077abd050757c257776"}]}