{"is_source_file": true, "description": "Simple scss file", "external_files": [], "external_methods": [], "published": [], "calls": [], "search-terms": [], "classes": [], "methods": [], "state": 2, "file_id": 59, "knowledge_revision": 348, "git_revision": "27824ec5860dd0d954c13ce3e13ea02eccfc4e6c", "filename": "scss/helpers/_stretched-link.scss", "hash": "1cd3650187aa8f6179952287b96335d4", "format-version": 4, "code-base-name": "https://github.com/kavia-common/bootstrap-2367.git:kavia-main", "revision_history": [{"348": "27824ec5860dd0d954c13ce3e13ea02eccfc4e6c"}]}