{"is_source_file": true, "format": "SCSS/SASS", "description": "This file contains styling definitions for a 'card' component, which is a common UI element, including base styles, optional textual caps, header navigation styles, image styles, and group layout styles.", "external_files": [], "external_methods": [], "published": [], "classes": [], "methods": [], "calls": ["border-radius(...)", "box-shadow(...)", "border-top-radius(...)", "border-bottom-radius(...)", "border-start-radius(...)", "border-end-radius(...)", "media-breakpoint-up(...)", "border(...)", "if(...)"], "search-terms": ["card", "bootstrap card style", "scss card component", "card header", "card footer", "card image", "card group", "scss variables"], "state": 2, "file_id": 359, "knowledge_revision": 1019, "git_revision": "c9cb0d679c174a770da7268e92ca43d66f068634", "hash": "e2b2d4e7bc1289166a1bf6fc81a4b251", "format-version": 4, "code-base-name": "bootstrap-2367", "filename": "scss/_card.scss", "revision_history": [{"1019": "c9cb0d679c174a770da7268e92ca43d66f068634"}]}