{"is_source_file": true, "format": "SCSS", "description": "This file defines a SCSS mixin named 'color-scheme' that applies styles based on the user's color scheme preference using media queries.", "external_files": [], "external_methods": [], "published": [], "classes": [], "methods": [{"name": "color-scheme", "description": "A SCSS mixin that applies styles conditionally based on the 'prefers-color-scheme' media feature."}], "calls": ["@media (prefers-color-scheme: #{$name})"], "search-terms": ["mixin-color-scheme", "color-scheme", "prefers-color-scheme", "scss mixin", "bootstrap", "media query"], "state": 2, "file_id": 343, "knowledge_revision": 1003, "git_revision": "4383ae0459e833679af985ccb67d0e627f9469de", "hash": "6f3cb289c06ab079b6cb6a1f2e74c819", "format-version": 4, "code-base-name": "bootstrap-2367", "filename": "scss/mixins/_color-scheme.scss", "revision_history": [{"1003": "4383ae0459e833679af985ccb67d0e627f9469de"}]}