{"is_source_file": true, "format": "SCSS (Sass)", "description": "This file defines styles for visually hidden elements, including a mixin 'visually-hidden' included into specific classes for accessibility purposes.", "external_files": [], "external_methods": ["visually-hidden() (mixin from related Sass code)"], "published": [], "classes": [], "methods": ["visually-hidden (mixin)"], "calls": ["@include visually-hidden()"], "search-terms": ["visually-hidden", "accessibility", "hidden styles", "scss mixin"], "state": 2, "file_id": 371, "knowledge_revision": 1029, "git_revision": "eae52b1cb0af18c5bf3fddd660f53d58d689cd63", "hash": "9b5a75ecdb0080663a8e4d2b6dcf6593", "format-version": 4, "code-base-name": "bootstrap-2367", "filename": "scss/helpers/_visually-hidden.scss", "revision_history": [{"1029": "eae52b1cb0af18c5bf3fddd660f53d58d689cd63"}]}