{"is_source_file": true, "format": "JavaScript", "description": "This file contains a JavaScript module that manages scrolling behavior for a sidebar navigation element in Bootstrap documentation. It ensures that the active sidebar link is scrolled into view within the sidebar container.", "external_files": ["https://getbootstrap.com/", "https://creativecommons.org/licenses/by/3.0/"], "external_methods": ["document.querySelector", "element.clientHeight", "element.offsetTop", "element.scrollTop"], "published": ["default"], "classes": [], "methods": [{"name": "default", "description": "An anonymous arrow function that adjusts the sidebar scroll position to bring the active link into view."}], "calls": ["document.querySelector('.bd-sidebar')", "document.querySelector('.bd-links-nav .active')"], "search-terms": ["sidebar scroll", "active link", "Bootstrap docs", "sidebar.js", "scrollIntoView"], "state": 2, "file_id": 155, "knowledge_revision": 460, "git_revision": "a8ab19955b7b4e66c7376b80a79a3563eb772621", "ctags": [], "filename": "site/src/assets/partials/sidebar.js", "hash": "752dd6b15f32ef98c5e785b67e9c7f8f", "format-version": 4, "code-base-name": "https://github.com/kavia-common/bootstrap-2367.git:kavia-main", "revision_history": [{"460": "a8ab19955b7b4e66c7376b80a79a3563eb772621"}]}