{"is_source_file": true, "format": "SCSS (Sass)", "description": "This file contains styles for clipboard and edit buttons used in code snippets, including positioning, display properties, and hover/focus states.", "external_files": [], "external_methods": [], "published": [], "classes": [], "methods": [], "calls": [], "search-terms": ["_clipboard-js.scss", "clipboard", "buttons", "styles", "Sass", "CSS"], "state": 2, "file_id": 124, "knowledge_revision": 425, "git_revision": "a8ab19955b7b4e66c7376b80a79a3563eb772621", "filename": "site/src/scss/_clipboard-js.scss", "hash": "70655aa4bba129986c572fef64f3c360", "format-version": 4, "code-base-name": "https://github.com/kavia-common/bootstrap-2367.git:kavia-main", "revision_history": [{"425": "a8ab19955b7b4e66c7376b80a79a3563eb772621"}]}